{
  "source": "atas_novaexportprovwap_v1",
  "pushed_at_utc": "2026-05-01T20:51:46Z",
  "bar_timestamp": "2026-05-01 22:19",
  "data": {
    "TIMESTAMP": "2026-05-01 22:19",
    "PRICE": 7251.5,
    "PRIOR_DAILY_HIGH": 7253.5,
    "PRIOR_DAILY_LOW": 7133.75,
    "PRIOR_DAILY_CLOSE": 7246.75,
    "PRIOR_DAILY_VAH": 7251.5,
    "PRIOR_DAILY_VAL": 7181.25,
    "PRIOR_DAILY_POC": 7244.5,
    "PRIOR_RTH_HIGH": 7253.5,
    "PRIOR_RTH_LOW": 7157.25,
    "PRIOR_RTH_CLOSE": 7251.5,
    "PRIOR_RTH_VAH": 7251.5,
    "PRIOR_RTH_VAL": 7189.75,
    "PRIOR_RTH_POC": 7244.5,
    "DAILY_VAH": 7279.75,
    "DAILY_VAL": 7255.75,
    "DAILY_POC": 7260.5,
    "GLOBEX_OPEN": 7256.0,
    "GLOBEX_VAH": 7266.0,
    "GLOBEX_VAL": 7259.0,
    "GLOBEX_POC": 7264.0,
    "W1_HIGH": 7265.75,
    "W1_LOW": 7246.25,
    "W2_HIGH": 7271.5,
    "W2_LOW": 7246.5,
    "RTH_OPEN": 7264.5,
    "RTH_VAH": 7279.75,
    "RTH_VAL": 7255.75,
    "RTH_POC": 7260.5,
    "IB_HIGH": 7300.75,
    "IB_LOW": 7258.75,
    "W3_HIGH": 7300.75,
    "W3_LOW": 7250.75,
    "VWAP_DAILY": 7273.04,
    "VWAP_WEEKLY": 7272.74,
    "VWAP_YTD": 7272.74,
    "DELTA_CURRENT": 1.0,
    "DELTA_CUMULATIVE": -6434699.0
  }
}