{
  "schema_version": "2.0",
  "source": "ibkr",
  "mode": "delayed_auto_roll",
  "snapshot_time": "2026-04-28 12:41:18 CET",
  "snapshot_time_utc": "2026-04-28T10:41:18Z",
  "age_seconds": 0,
  "age_minutes": 0.0,
  "freshness": "OK",
  "session_context": {
    "timezone": "Europe/Berlin",
    "current_time_cet": "12:41 CET",
    "is_rth_us": false,
    "is_eth_us": true,
    "is_europe_open": true,
    "is_asia_session": false,
    "next_scheduled_sweep": "afternoon",
    "reference_close_label": "prior_us_rth_close",
    "reference_close_time_utc": "2026-04-27T20:00:00Z"
  },
  "market_summary": {
    "equity_tone": "flat",
    "rates_tone": "neutral",
    "oil_tone": "up",
    "gold_tone": "down",
    "vol_tone": "flat",
    "usd_tone": "mixed",
    "cross_asset_alignment": "mixed",
    "edna_regime_hint": "below_close_watch"
  },
  "sector_rotation": {
    "available": true,
    "leaders": [
      "XLE",
      "XLF",
      "XLP"
    ],
    "laggards": [
      "XLY",
      "XLI",
      "XLK"
    ],
    "rotation_theme": "defensive_rotation",
    "sectors_up": 6,
    "sectors_down": 4,
    "breadth": "6/11 sectors advancing",
    "breadth_score": "mixed",
    "offensive_avg_chg_pct": 0.13,
    "defensive_avg_chg_pct": 0.23,
    "offense_defense_spread": -0.1,
    "offense_defense_score": "neutral",
    "ranked": [
      {
        "symbol": "XLE",
        "sector": "Energy",
        "classification": "offensive",
        "change_pct": 1.6,
        "rel_vs_es_pct": 1.83
      },
      {
        "symbol": "XLF",
        "sector": "Financials",
        "classification": "offensive",
        "change_pct": 0.44,
        "rel_vs_es_pct": 0.67
      },
      {
        "symbol": "XLP",
        "sector": "Consumer Staples",
        "classification": "defensive",
        "change_pct": 0.43,
        "rel_vs_es_pct": 0.66
      },
      {
        "symbol": "XLV",
        "sector": "Health Care",
        "classification": "defensive",
        "change_pct": 0.24,
        "rel_vs_es_pct": 0.47
      },
      {
        "symbol": "XLU",
        "sector": "Utilities",
        "classification": "defensive",
        "change_pct": 0.24,
        "rel_vs_es_pct": 0.47
      },
      {
        "symbol": "XLC",
        "sector": "Communication Services",
        "classification": "offensive",
        "change_pct": 0.15,
        "rel_vs_es_pct": 0.38
      },
      {
        "symbol": "XLRE",
        "sector": "Real Estate",
        "classification": "defensive",
        "change_pct": 0.0,
        "rel_vs_es_pct": 0.23
      },
      {
        "symbol": "XLB",
        "sector": "Materials",
        "classification": "offensive",
        "change_pct": -0.04,
        "rel_vs_es_pct": 0.19
      },
      {
        "symbol": "XLY",
        "sector": "Consumer Discretionary",
        "classification": "offensive",
        "change_pct": -0.06,
        "rel_vs_es_pct": 0.17
      },
      {
        "symbol": "XLI",
        "sector": "Industrials",
        "classification": "offensive",
        "change_pct": -0.08,
        "rel_vs_es_pct": 0.15
      },
      {
        "symbol": "XLK",
        "sector": "Technology",
        "classification": "offensive",
        "change_pct": -1.11,
        "rel_vs_es_pct": -0.88
      }
    ]
  },
  "credit_analysis": {
    "available": true,
    "hyg_change_pct": 0.0,
    "jnk_change_pct": 0.0,
    "lqd_change_pct": -0.22,
    "tlt_change_pct": -0.23,
    "ief_change_pct": -0.14,
    "high_yield_avg_pct": 0.0,
    "treasury_avg_pct": -0.18,
    "hy_vs_ig_spread": 0.22,
    "hy_vs_treasury_spread": 0.18,
    "credit_risk_score": "neutral",
    "credit_vs_treasury_score": "neutral",
    "flight_to_quality_flag": false
  },
  "assets": {
    "ES": {
      "label": "E-mini S&P 500",
      "root_symbol": "ES",
      "provider_symbol": "ESM6",
      "exchange": "CME",
      "asset_class": "future",
      "currency": "USD",
      "time": "2026-04-28 12:40:04 CET",
      "time_utc": "2026-04-28T10:40:04Z",
      "age_seconds": 3,
      "freshness": "OK",
      "last": 7189.25,
      "bid": 7189.0,
      "ask": 7189.25,
      "mid": 7189.125,
      "close": 7206.0,
      "change_abs": -16.75,
      "change_pct": -0.23,
      "session": {
        "overnight_open": 7204.75,
        "overnight_high": 7223.25,
        "overnight_low": 7186.0,
        "prior_rth_close": 7206.0,
        "europe_open_price": 7198.25,
        "us_open_price": null,
        "move_since_europe_open_pct": -0.13,
        "move_since_us_open_pct": null,
        "overnight_range_points": 37.25,
        "overnight_position_in_range": 0.087
      },
      "derived": {
        "direction_vs_close": "down",
        "overnight_regime": "trend_down",
        "above_prior_rth_close": false,
        "above_europe_open": false,
        "stretch_vs_close_points": -16.75,
        "stretch_vs_close_pct": -0.23
      },
      "status": "OK"
    },
    "NQ": {
      "label": "Nasdaq-100 Futures",
      "root_symbol": "NQ",
      "provider_symbol": "NQM6",
      "exchange": "CME",
      "asset_class": "future",
      "currency": "USD",
      "time": "2026-04-28 12:40:07 CET",
      "time_utc": "2026-04-28T10:40:07Z",
      "age_seconds": 6,
      "freshness": "OK",
      "last": 27269.0,
      "bid": 27268.75,
      "ask": 27269.75,
      "mid": 27269.25,
      "close": 27440.5,
      "change_abs": -171.5,
      "change_pct": -0.62,
      "session": {
        "overnight_open": 27423.0,
        "overnight_high": 27512.0,
        "overnight_low": 27251.0,
        "prior_rth_close": 27440.5,
        "europe_open_price": 27363.0,
        "us_open_price": null,
        "move_since_europe_open_pct": -0.34,
        "move_since_us_open_pct": null,
        "overnight_range_points": 261.0,
        "overnight_position_in_range": 0.069
      },
      "derived": {
        "direction_vs_close": "down",
        "overnight_regime": "trend_down",
        "above_prior_rth_close": false,
        "above_europe_open": false,
        "stretch_vs_close_points": -171.5,
        "stretch_vs_close_pct": -0.62
      },
      "status": "OK"
    },
    "RTY": {
      "label": "Russell 2000 Futures",
      "root_symbol": "RTY",
      "provider_symbol": "RTYM6",
      "exchange": "CME",
      "asset_class": "future",
      "currency": "USD",
      "time": "2026-04-28 12:40:10 CET",
      "time_utc": "2026-04-28T10:40:10Z",
      "age_seconds": 9,
      "freshness": "OK",
      "last": 2791.3,
      "bid": 2791.3,
      "ask": 2791.5,
      "mid": 2791.4,
      "close": 2799.6,
      "change_abs": -8.3,
      "change_pct": -0.3,
      "session": {
        "overnight_open": 2799.3,
        "overnight_high": 2809.5,
        "overnight_low": 2790.1,
        "prior_rth_close": 2799.6,
        "europe_open_price": 2798.7,
        "us_open_price": null,
        "move_since_europe_open_pct": -0.26,
        "move_since_us_open_pct": null,
        "overnight_range_points": 19.4,
        "overnight_position_in_range": 0.062
      },
      "derived": {
        "direction_vs_close": "down",
        "overnight_regime": "trend_down",
        "above_prior_rth_close": false,
        "above_europe_open": false,
        "stretch_vs_close_points": -8.3,
        "stretch_vs_close_pct": -0.3
      },
      "status": "OK"
    },
    "YM": {
      "label": "Dow Jones Futures",
      "root_symbol": "YM",
      "provider_symbol": "YMM6",
      "exchange": "CBOT",
      "asset_class": "future",
      "currency": "USD",
      "time": "2026-04-28 12:40:13 CET",
      "time_utc": "2026-04-28T10:40:13Z",
      "age_seconds": 12,
      "freshness": "OK",
      "last": 49468.0,
      "bid": 49466.0,
      "ask": 49469.0,
      "mid": 49467.5,
      "close": 49342.0,
      "change_abs": 126.0,
      "change_pct": 0.26,
      "session": {
        "overnight_open": 49347.0,
        "overnight_high": 49513.0,
        "overnight_low": 49320.0,
        "prior_rth_close": 49342.0,
        "europe_open_price": 49352.0,
        "us_open_price": null,
        "move_since_europe_open_pct": 0.24,
        "move_since_us_open_pct": null,
        "overnight_range_points": 193.0,
        "overnight_position_in_range": 0.767
      },
      "derived": {
        "direction_vs_close": "up",
        "overnight_regime": "trend_up",
        "above_prior_rth_close": true,
        "above_europe_open": true,
        "stretch_vs_close_points": 126.0,
        "stretch_vs_close_pct": 0.26
      },
      "status": "OK"
    },
    "CL": {
      "label": "Crude Oil Futures",
      "root_symbol": "CL",
      "provider_symbol": "CLM6",
      "exchange": "NYMEX",
      "asset_class": "future",
      "currency": "USD",
      "time": "2026-04-28 12:40:16 CET",
      "time_utc": "2026-04-28T10:40:16Z",
      "age_seconds": 15,
      "freshness": "OK",
      "last": 99.73,
      "bid": 99.72,
      "ask": 99.74,
      "mid": 99.73,
      "close": 96.37,
      "change_abs": 3.36,
      "change_pct": 3.49,
      "session": {
        "overnight_open": 96.67,
        "overnight_high": 100.11,
        "overnight_low": 96.24,
        "prior_rth_close": 96.37,
        "europe_open_price": 98.22,
        "us_open_price": null,
        "move_since_europe_open_pct": 1.54,
        "move_since_us_open_pct": null,
        "overnight_range_points": 3.87,
        "overnight_position_in_range": 0.902
      },
      "derived": {
        "direction_vs_close": "up",
        "overnight_regime": "trend_up",
        "above_prior_rth_close": true,
        "above_europe_open": true,
        "stretch_vs_close_points": 3.36,
        "stretch_vs_close_pct": 3.49
      },
      "status": "OK"
    },
    "GC": {
      "label": "Gold Futures",
      "root_symbol": "GC",
      "provider_symbol": "GCK6",
      "exchange": "COMEX",
      "asset_class": "future",
      "currency": "USD",
      "time": "2026-04-28 12:40:19 CET",
      "time_utc": "2026-04-28T10:40:19Z",
      "age_seconds": 18,
      "freshness": "OK",
      "last": 4607.5,
      "bid": 4609.5,
      "ask": 4610.1,
      "mid": 4609.8,
      "close": 4676.9,
      "change_abs": -69.4,
      "change_pct": -1.48,
      "session": {
        "overnight_open": 4682.5,
        "overnight_high": 4698.4,
        "overnight_low": 4607.3,
        "prior_rth_close": 4676.9,
        "europe_open_price": 4632.8,
        "us_open_price": null,
        "move_since_europe_open_pct": -0.55,
        "move_since_us_open_pct": null,
        "overnight_range_points": 91.1,
        "overnight_position_in_range": 0.002
      },
      "derived": {
        "direction_vs_close": "down",
        "overnight_regime": "trend_down",
        "above_prior_rth_close": false,
        "above_europe_open": false,
        "stretch_vs_close_points": -69.4,
        "stretch_vs_close_pct": -1.48
      },
      "status": "OK"
    },
    "ZN": {
      "label": "10Y Treasury Futures",
      "root_symbol": "ZN",
      "provider_symbol": "ZNM6",
      "exchange": "CBOT",
      "asset_class": "future",
      "currency": "USD",
      "time": "2026-04-28 12:40:22 CET",
      "time_utc": "2026-04-28T10:40:22Z",
      "age_seconds": 22,
      "freshness": "OK",
      "last": 110.90625,
      "bid": 110.890625,
      "ask": 110.90625,
      "mid": 110.8984,
      "close": 111.03125,
      "change_abs": -0.125,
      "change_pct": -0.11,
      "session": {
        "overnight_open": 111.015625,
        "overnight_high": 111.078125,
        "overnight_low": 110.8125,
        "prior_rth_close": 111.03125,
        "europe_open_price": 110.9375,
        "us_open_price": null,
        "move_since_europe_open_pct": -0.03,
        "move_since_us_open_pct": null,
        "overnight_range_points": 0.2656,
        "overnight_position_in_range": 0.353
      },
      "derived": {
        "direction_vs_close": "down",
        "overnight_regime": "balanced",
        "above_prior_rth_close": false,
        "above_europe_open": false,
        "stretch_vs_close_points": -0.125,
        "stretch_vs_close_pct": -0.11
      },
      "status": "OK"
    },
    "ZT": {
      "label": "2Y Treasury Futures",
      "root_symbol": "ZT",
      "provider_symbol": "ZTM6",
      "exchange": "CBOT",
      "asset_class": "future",
      "currency": "USD",
      "time": "2026-04-28 12:40:26 CET",
      "time_utc": "2026-04-28T10:40:26Z",
      "age_seconds": 25,
      "freshness": "OK",
      "last": 103.6875,
      "bid": 103.6875,
      "ask": 103.69140625,
      "mid": 103.6895,
      "close": 103.72265625,
      "change_abs": -0.0352,
      "change_pct": -0.03,
      "session": {
        "overnight_open": 103.73046875,
        "overnight_high": 103.73828125,
        "overnight_low": 103.6640625,
        "prior_rth_close": 103.72265625,
        "europe_open_price": 103.703125,
        "us_open_price": null,
        "move_since_europe_open_pct": -0.02,
        "move_since_us_open_pct": null,
        "overnight_range_points": 0.0742,
        "overnight_position_in_range": 0.316
      },
      "derived": {
        "direction_vs_close": "down",
        "overnight_regime": "balanced",
        "above_prior_rth_close": false,
        "above_europe_open": false,
        "stretch_vs_close_points": -0.0352,
        "stretch_vs_close_pct": -0.03
      },
      "status": "OK"
    },
    "DX": {
      "label": "US Dollar Index Futures",
      "root_symbol": "DX",
      "provider_symbol": "DXM6",
      "exchange": "NYBOT",
      "asset_class": "future",
      "currency": "USD",
      "time": "2026-04-28 12:40:29 CET",
      "time_utc": "2026-04-28T10:40:29Z",
      "age_seconds": 28,
      "freshness": "OK",
      "last": 98.59,
      "bid": 98.58,
      "ask": 98.585,
      "mid": 98.5825,
      "close": 98.32,
      "change_abs": 0.27,
      "change_pct": 0.27,
      "session": {
        "overnight_open": 98.28,
        "overnight_high": 98.605,
        "overnight_low": 98.26,
        "prior_rth_close": 98.32,
        "europe_open_price": 98.415,
        "us_open_price": null,
        "move_since_europe_open_pct": 0.18,
        "move_since_us_open_pct": null,
        "overnight_range_points": 0.345,
        "overnight_position_in_range": 0.957
      },
      "derived": {
        "direction_vs_close": "up",
        "overnight_regime": "trend_up",
        "above_prior_rth_close": true,
        "above_europe_open": true,
        "stretch_vs_close_points": 0.27,
        "stretch_vs_close_pct": 0.27
      },
      "status": "OK"
    },
    "VIX": {
      "label": "VIX Futures",
      "root_symbol": "VIX",
      "provider_symbol": "VX17J6",
      "exchange": "CFE",
      "asset_class": "future",
      "currency": "USD",
      "time": "2026-04-28 12:40:32 CET",
      "time_utc": "2026-04-28T10:40:32Z",
      "age_seconds": 31,
      "freshness": "OK",
      "last": 20.05,
      "bid": 15.75,
      "ask": null,
      "mid": null,
      "close": 20.05,
      "change_abs": 0.0,
      "change_pct": 0.0,
      "session": {
        "overnight_open": null,
        "overnight_high": null,
        "overnight_low": null,
        "prior_rth_close": 20.05,
        "europe_open_price": null,
        "us_open_price": null,
        "move_since_europe_open_pct": null,
        "move_since_us_open_pct": null,
        "overnight_range_points": null,
        "overnight_position_in_range": null
      },
      "derived": {
        "direction_vs_close": "flat",
        "overnight_regime": null,
        "above_prior_rth_close": false,
        "above_europe_open": null,
        "stretch_vs_close_points": 0.0,
        "stretch_vs_close_pct": 0.0
      },
      "status": "OK"
    },
    "DAX": {
      "label": "DAX Futures",
      "root_symbol": "DAX",
      "provider_symbol": "FDXM 20260619 M",
      "exchange": "EUREX",
      "asset_class": "future",
      "currency": "EUR",
      "time": "2026-04-28 12:40:35 CET",
      "time_utc": "2026-04-28T10:40:35Z",
      "age_seconds": 34,
      "freshness": "OK",
      "last": 24243.0,
      "bid": 24243.0,
      "ask": 24246.0,
      "mid": 24244.5,
      "close": 24221.0,
      "change_abs": 22.0,
      "change_pct": 0.09,
      "session": {
        "overnight_open": 24290.0,
        "overnight_high": 24294.0,
        "overnight_low": 24118.0,
        "prior_rth_close": 24221.0,
        "europe_open_price": 24218.0,
        "us_open_price": null,
        "move_since_europe_open_pct": 0.1,
        "move_since_us_open_pct": null,
        "overnight_range_points": 176.0,
        "overnight_position_in_range": 0.71
      },
      "derived": {
        "direction_vs_close": "up",
        "overnight_regime": "trend_up",
        "above_prior_rth_close": true,
        "above_europe_open": true,
        "stretch_vs_close_points": 22.0,
        "stretch_vs_close_pct": 0.09
      },
      "status": "OK"
    },
    "ESTX50": {
      "label": "Euro Stoxx 50 Futures",
      "root_symbol": "ESTX50",
      "provider_symbol": "FESX 20260619 M",
      "exchange": "EUREX",
      "asset_class": "future",
      "currency": "EUR",
      "time": "2026-04-28 12:40:38 CET",
      "time_utc": "2026-04-28T10:40:38Z",
      "age_seconds": 37,
      "freshness": "OK",
      "last": 5830.0,
      "bid": 5829.0,
      "ask": 5830.0,
      "mid": 5829.5,
      "close": 5812.0,
      "change_abs": 18.0,
      "change_pct": 0.31,
      "session": {
        "overnight_open": 5837.0,
        "overnight_high": 5840.0,
        "overnight_low": 5801.0,
        "prior_rth_close": 5812.0,
        "europe_open_price": 5815.0,
        "us_open_price": null,
        "move_since_europe_open_pct": 0.26,
        "move_since_us_open_pct": null,
        "overnight_range_points": 39.0,
        "overnight_position_in_range": 0.744
      },
      "derived": {
        "direction_vs_close": "up",
        "overnight_regime": "trend_up",
        "above_prior_rth_close": true,
        "above_europe_open": true,
        "stretch_vs_close_points": 18.0,
        "stretch_vs_close_pct": 0.31
      },
      "status": "OK"
    },
    "NKD": {
      "label": "Nikkei 225 Futures",
      "root_symbol": "NKD",
      "provider_symbol": "NKDM6",
      "exchange": "CME",
      "asset_class": "future",
      "currency": "USD",
      "time": "2026-04-28 12:40:41 CET",
      "time_utc": "2026-04-28T10:40:41Z",
      "age_seconds": 40,
      "freshness": "OK",
      "last": 59835.0,
      "bid": 59835.0,
      "ask": 59845.0,
      "mid": 59840.0,
      "close": 60245.0,
      "change_abs": -410.0,
      "change_pct": -0.68,
      "session": {
        "overnight_open": 60230.0,
        "overnight_high": 60540.0,
        "overnight_low": 59800.0,
        "prior_rth_close": 60245.0,
        "europe_open_price": 59920.0,
        "us_open_price": null,
        "move_since_europe_open_pct": -0.14,
        "move_since_us_open_pct": null,
        "overnight_range_points": 740.0,
        "overnight_position_in_range": 0.047
      },
      "derived": {
        "direction_vs_close": "down",
        "overnight_regime": "trend_down",
        "above_prior_rth_close": false,
        "above_europe_open": false,
        "stretch_vs_close_points": -410.0,
        "stretch_vs_close_pct": -0.68
      },
      "status": "OK"
    },
    "EURUSD": {
      "label": "Euro / US Dollar",
      "root_symbol": "EURUSD",
      "provider_symbol": "EURUSD",
      "exchange": "IDEALPRO",
      "asset_class": "fx",
      "currency": "USD",
      "time": "2026-04-28 12:40:43 CET",
      "time_utc": "2026-04-28T10:40:43Z",
      "age_seconds": 42,
      "freshness": "OK",
      "last": 1.16955,
      "bid": 1.16954,
      "ask": 1.16958,
      "mid": 1.16956,
      "close": 1.1721,
      "change_abs": -0.00255,
      "change_pct": -0.2176,
      "session": null,
      "derived": null,
      "status": "OK"
    },
    "USDJPY": {
      "label": "US Dollar / Japanese Yen",
      "root_symbol": "USDJPY",
      "provider_symbol": "USDJPY",
      "exchange": "IDEALPRO",
      "asset_class": "fx",
      "currency": "JPY",
      "time": "2026-04-28 12:40:45 CET",
      "time_utc": "2026-04-28T10:40:45Z",
      "age_seconds": 44,
      "freshness": "OK",
      "last": 159.61,
      "bid": 159.608,
      "ask": 159.611,
      "mid": 159.6095,
      "close": 159.42,
      "change_abs": 0.19,
      "change_pct": 0.1192,
      "session": null,
      "derived": null,
      "status": "OK"
    },
    "XLK": {
      "label": "SPDR Technology ETF",
      "root_symbol": "XLK",
      "provider_symbol": "XLK",
      "exchange": "SMART",
      "asset_class": "etf",
      "sector": "Technology",
      "classification": "offensive",
      "currency": "USD",
      "time": "2026-04-28 12:40:47 CET",
      "time_utc": "2026-04-28T10:40:47Z",
      "age_seconds": 46,
      "freshness": "OK",
      "last": 158.78,
      "bid": 158.55,
      "ask": 158.79,
      "mid": 158.67,
      "close": 160.57,
      "change_abs": -1.79,
      "change_pct": -1.11,
      "session": null,
      "derived": null,
      "status": "OK"
    },
    "XLF": {
      "label": "SPDR Financials ETF",
      "root_symbol": "XLF",
      "provider_symbol": "XLF",
      "exchange": "SMART",
      "asset_class": "etf",
      "sector": "Financials",
      "classification": "offensive",
      "currency": "USD",
      "time": "2026-04-28 12:40:49 CET",
      "time_utc": "2026-04-28T10:40:49Z",
      "age_seconds": 48,
      "freshness": "OK",
      "last": 52.04,
      "bid": 52.01,
      "ask": 52.05,
      "mid": 52.03,
      "close": 51.81,
      "change_abs": 0.23,
      "change_pct": 0.44,
      "session": null,
      "derived": null,
      "status": "OK"
    },
    "XLV": {
      "label": "SPDR Health Care ETF",
      "root_symbol": "XLV",
      "provider_symbol": "XLV",
      "exchange": "SMART",
      "asset_class": "etf",
      "sector": "Health Care",
      "classification": "defensive",
      "currency": "USD",
      "time": "2026-04-28 12:40:51 CET",
      "time_utc": "2026-04-28T10:40:51Z",
      "age_seconds": 50,
      "freshness": "OK",
      "last": 143.8,
      "bid": 143.86,
      "ask": 144.25,
      "mid": 144.055,
      "close": 143.46,
      "change_abs": 0.34,
      "change_pct": 0.24,
      "session": null,
      "derived": null,
      "status": "OK"
    },
    "XLY": {
      "label": "SPDR Consumer Discretionary ETF",
      "root_symbol": "XLY",
      "provider_symbol": "XLY",
      "exchange": "SMART",
      "asset_class": "etf",
      "sector": "Consumer Discretionary",
      "classification": "offensive",
      "currency": "USD",
      "time": "2026-04-28 12:40:53 CET",
      "time_utc": "2026-04-28T10:40:53Z",
      "age_seconds": 52,
      "freshness": "OK",
      "last": 117.77,
      "bid": 117.69,
      "ask": 117.89,
      "mid": 117.79,
      "close": 117.84,
      "change_abs": -0.07,
      "change_pct": -0.06,
      "session": null,
      "derived": null,
      "status": "OK"
    },
    "XLP": {
      "label": "SPDR Consumer Staples ETF",
      "root_symbol": "XLP",
      "provider_symbol": "XLP",
      "exchange": "SMART",
      "asset_class": "etf",
      "sector": "Consumer Staples",
      "classification": "defensive",
      "currency": "USD",
      "time": "2026-04-28 12:40:55 CET",
      "time_utc": "2026-04-28T10:40:55Z",
      "age_seconds": 54,
      "freshness": "OK",
      "last": 82.69,
      "bid": 82.38,
      "ask": 83.45,
      "mid": 82.915,
      "close": 82.34,
      "change_abs": 0.35,
      "change_pct": 0.43,
      "session": null,
      "derived": null,
      "status": "OK"
    },
    "XLE": {
      "label": "SPDR Energy ETF",
      "root_symbol": "XLE",
      "provider_symbol": "XLE",
      "exchange": "SMART",
      "asset_class": "etf",
      "sector": "Energy",
      "classification": "offensive",
      "currency": "USD",
      "time": "2026-04-28 12:40:57 CET",
      "time_utc": "2026-04-28T10:40:57Z",
      "age_seconds": 56,
      "freshness": "OK",
      "last": 57.68,
      "bid": 57.65,
      "ask": 57.68,
      "mid": 57.665,
      "close": 56.77,
      "change_abs": 0.91,
      "change_pct": 1.6,
      "session": null,
      "derived": null,
      "status": "OK"
    },
    "XLI": {
      "label": "SPDR Industrials ETF",
      "root_symbol": "XLI",
      "provider_symbol": "XLI",
      "exchange": "SMART",
      "asset_class": "etf",
      "sector": "Industrials",
      "classification": "offensive",
      "currency": "USD",
      "time": "2026-04-28 12:40:59 CET",
      "time_utc": "2026-04-28T10:40:59Z",
      "age_seconds": 58,
      "freshness": "OK",
      "last": 172.37,
      "bid": 169.98,
      "ask": 175.03,
      "mid": 172.505,
      "close": 172.51,
      "change_abs": -0.14,
      "change_pct": -0.08,
      "session": null,
      "derived": null,
      "status": "OK"
    },
    "XLB": {
      "label": "SPDR Materials ETF",
      "root_symbol": "XLB",
      "provider_symbol": "XLB",
      "exchange": "SMART",
      "asset_class": "etf",
      "sector": "Materials",
      "classification": "offensive",
      "currency": "USD",
      "time": "2026-04-28 12:41:01 CET",
      "time_utc": "2026-04-28T10:41:01Z",
      "age_seconds": 60,
      "freshness": "OK",
      "last": 51.76,
      "bid": 51.67,
      "ask": 53.5,
      "mid": 52.585,
      "close": 51.78,
      "change_abs": -0.02,
      "change_pct": -0.04,
      "session": null,
      "derived": null,
      "status": "OK"
    },
    "XLRE": {
      "label": "SPDR Real Estate ETF",
      "root_symbol": "XLRE",
      "provider_symbol": "XLRE",
      "exchange": "SMART",
      "asset_class": "etf",
      "sector": "Real Estate",
      "classification": "defensive",
      "currency": "USD",
      "time": "2026-04-28 12:41:03 CET",
      "time_utc": "2026-04-28T10:41:03Z",
      "age_seconds": 63,
      "freshness": "OK",
      "last": 43.49,
      "bid": 43.43,
      "ask": 43.67,
      "mid": 43.55,
      "close": 43.49,
      "change_abs": 0.0,
      "change_pct": 0.0,
      "session": null,
      "derived": null,
      "status": "OK"
    },
    "XLU": {
      "label": "SPDR Utilities ETF",
      "root_symbol": "XLU",
      "provider_symbol": "XLU",
      "exchange": "SMART",
      "asset_class": "etf",
      "sector": "Utilities",
      "classification": "defensive",
      "currency": "USD",
      "time": "2026-04-28 12:41:05 CET",
      "time_utc": "2026-04-28T10:41:05Z",
      "age_seconds": 65,
      "freshness": "OK",
      "last": 46.3,
      "bid": 46.19,
      "ask": 46.49,
      "mid": 46.34,
      "close": 46.19,
      "change_abs": 0.11,
      "change_pct": 0.24,
      "session": null,
      "derived": null,
      "status": "OK"
    },
    "XLC": {
      "label": "SPDR Communication Services ETF",
      "root_symbol": "XLC",
      "provider_symbol": "XLC",
      "exchange": "SMART",
      "asset_class": "etf",
      "sector": "Communication Services",
      "classification": "offensive",
      "currency": "USD",
      "time": "2026-04-28 12:41:07 CET",
      "time_utc": "2026-04-28T10:41:07Z",
      "age_seconds": 67,
      "freshness": "OK",
      "last": 115.98,
      "bid": 115.0,
      "ask": 116.29,
      "mid": 115.645,
      "close": 115.81,
      "change_abs": 0.17,
      "change_pct": 0.15,
      "session": null,
      "derived": null,
      "status": "OK"
    },
    "HYG": {
      "label": "iShares High Yield Corp Bond ETF",
      "root_symbol": "HYG",
      "provider_symbol": "HYG",
      "exchange": "SMART",
      "asset_class": "etf",
      "credit_type": "high_yield",
      "currency": "USD",
      "time": "2026-04-28 12:41:09 CET",
      "time_utc": "2026-04-28T10:41:09Z",
      "age_seconds": 69,
      "freshness": "OK",
      "last": 80.51,
      "bid": 80.35,
      "ask": 80.53,
      "mid": 80.44,
      "close": 80.51,
      "change_abs": 0.0,
      "change_pct": 0.0,
      "session": null,
      "derived": null,
      "status": "OK"
    },
    "JNK": {
      "label": "SPDR Bloomberg High Yield Bond ETF",
      "root_symbol": "JNK",
      "provider_symbol": "JNK",
      "exchange": "SMART",
      "asset_class": "etf",
      "credit_type": "high_yield",
      "currency": "USD",
      "time": "2026-04-28 12:41:11 CET",
      "time_utc": "2026-04-28T10:41:11Z",
      "age_seconds": 71,
      "freshness": "OK",
      "last": 96.91,
      "bid": 96.31,
      "ask": 97.85,
      "mid": 97.08,
      "close": 96.91,
      "change_abs": 0.0,
      "change_pct": 0.0,
      "session": null,
      "derived": null,
      "status": "OK"
    },
    "LQD": {
      "label": "iShares Investment Grade Corp Bond ETF",
      "root_symbol": "LQD",
      "provider_symbol": "LQD",
      "exchange": "SMART",
      "asset_class": "etf",
      "credit_type": "invest_grade",
      "currency": "USD",
      "time": "2026-04-28 12:41:14 CET",
      "time_utc": "2026-04-28T10:41:14Z",
      "age_seconds": 73,
      "freshness": "OK",
      "last": 109.05,
      "bid": 109.02,
      "ask": 109.21,
      "mid": 109.115,
      "close": 109.29,
      "change_abs": -0.24,
      "change_pct": -0.22,
      "session": null,
      "derived": null,
      "status": "OK"
    },
    "TLT": {
      "label": "iShares 20+ Year Treasury Bond ETF",
      "root_symbol": "TLT",
      "provider_symbol": "TLT",
      "exchange": "SMART",
      "asset_class": "etf",
      "credit_type": "treasury",
      "currency": "USD",
      "time": "2026-04-28 12:41:16 CET",
      "time_utc": "2026-04-28T10:41:16Z",
      "age_seconds": 75,
      "freshness": "OK",
      "last": 86.08,
      "bid": 86.07,
      "ask": 86.08,
      "mid": 86.075,
      "close": 86.28,
      "change_abs": -0.2,
      "change_pct": -0.23,
      "session": null,
      "derived": null,
      "status": "OK"
    },
    "IEF": {
      "label": "iShares 7-10 Year Treasury Bond ETF",
      "root_symbol": "IEF",
      "provider_symbol": "IEF",
      "exchange": "SMART",
      "asset_class": "etf",
      "credit_type": "treasury",
      "currency": "USD",
      "time": "2026-04-28 12:41:18 CET",
      "time_utc": "2026-04-28T10:41:18Z",
      "age_seconds": 77,
      "freshness": "OK",
      "last": 95.21,
      "bid": 95.19,
      "ask": 95.28,
      "mid": 95.235,
      "close": 95.34,
      "change_abs": -0.13,
      "change_pct": -0.14,
      "session": null,
      "derived": null,
      "status": "OK"
    }
  },
  "truth_tellers": {
    "primary": [
      "CL",
      "GC",
      "NKD",
      "NQ"
    ],
    "secondary": [
      "ESTX50",
      "RTY",
      "DX"
    ],
    "notes": "No notable divergences."
  },
  "alerts": [
    {
      "level": "info",
      "code": "ES_BELOW_PRIOR_CLOSE",
      "message": "ES trading below prior RTH close."
    },
    {
      "level": "info",
      "code": "CL_LARGE_MOVE",
      "message": "CL up 3.49% vs prior close."
    },
    {
      "level": "warning",
      "code": "SECTOR_DEFENSIVE_ROTATION",
      "message": "Defensive rotation detected \u2014 leaders: ['XLE', 'XLF', 'XLP']."
    }
  ],
  "errors": []
}