{
  "schema_version": "2.0",
  "source": "ibkr",
  "mode": "delayed_auto_roll",
  "snapshot_time": "2026-04-30 17:01:18 CET",
  "snapshot_time_utc": "2026-04-30T15:01:18Z",
  "age_seconds": 0,
  "age_minutes": 0.0,
  "freshness": "OK",
  "session_context": {
    "timezone": "Europe/Berlin",
    "current_time_cet": "17:01 CET",
    "is_rth_us": true,
    "is_eth_us": false,
    "is_europe_open": true,
    "is_asia_session": false,
    "next_scheduled_sweep": "after_close",
    "reference_close_label": "prior_us_rth_close",
    "reference_close_time_utc": "2026-04-29T20:00:00Z"
  },
  "market_summary": {
    "equity_tone": "mildly_up",
    "rates_tone": "neutral",
    "oil_tone": "flat",
    "gold_tone": "up",
    "vol_tone": "flat",
    "usd_tone": "usd_weakness",
    "cross_asset_alignment": "mild_risk_on",
    "edna_regime_hint": "above_close_watch"
  },
  "sector_rotation": {
    "available": true,
    "leaders": [
      "XLU",
      "XLRE"
    ],
    "laggards": [
      "XLU",
      "XLRE"
    ],
    "rotation_theme": "mixed",
    "sectors_up": 2,
    "sectors_down": 0,
    "breadth": "2/2 sectors advancing",
    "breadth_score": "very_narrow",
    "offensive_avg_chg_pct": null,
    "defensive_avg_chg_pct": 1.74,
    "offense_defense_spread": null,
    "offense_defense_score": "unavailable",
    "ranked": [
      {
        "symbol": "XLU",
        "sector": "Utilities",
        "classification": "defensive",
        "change_pct": 2.39,
        "rel_vs_es_pct": 2.21
      },
      {
        "symbol": "XLRE",
        "sector": "Real Estate",
        "classification": "defensive",
        "change_pct": 1.08,
        "rel_vs_es_pct": 0.9
      }
    ]
  },
  "credit_analysis": {
    "available": true,
    "hyg_change_pct": 0.19,
    "jnk_change_pct": 0.19,
    "lqd_change_pct": null,
    "tlt_change_pct": 0.07,
    "ief_change_pct": 0.19,
    "high_yield_avg_pct": 0.19,
    "treasury_avg_pct": 0.13,
    "hy_vs_ig_spread": null,
    "hy_vs_treasury_spread": 0.06,
    "credit_risk_score": "mildly_risk_on",
    "credit_vs_treasury_score": "neutral",
    "flight_to_quality_flag": false
  },
  "assets": {
    "ES": {
      "label": "E-mini S&P 500",
      "root_symbol": "ES",
      "provider_symbol": "ESM6",
      "exchange": "CME",
      "asset_class": "future",
      "currency": "USD",
      "time": "2026-04-30 17:00:04 CET",
      "time_utc": "2026-04-30T15:00:04Z",
      "age_seconds": 3,
      "freshness": "OK",
      "last": 7181.25,
      "bid": 7181.25,
      "ask": 7181.5,
      "mid": 7181.375,
      "close": 7168.0,
      "change_abs": 13.25,
      "change_pct": 0.18,
      "session": {
        "overnight_open": 7150.0,
        "overnight_high": 7211.5,
        "overnight_low": 7133.75,
        "prior_rth_close": 7168.0,
        "europe_open_price": 7143.25,
        "us_open_price": 7204.0,
        "move_since_europe_open_pct": 0.53,
        "move_since_us_open_pct": -0.32,
        "overnight_range_points": 77.75,
        "overnight_position_in_range": 0.611
      },
      "derived": {
        "direction_vs_close": "up",
        "overnight_regime": "balanced",
        "above_prior_rth_close": true,
        "above_europe_open": true,
        "stretch_vs_close_points": 13.25,
        "stretch_vs_close_pct": 0.18
      },
      "status": "OK"
    },
    "NQ": {
      "label": "Nasdaq-100 Futures",
      "root_symbol": "NQ",
      "provider_symbol": "NQM6",
      "exchange": "CME",
      "asset_class": "future",
      "currency": "USD",
      "time": "2026-04-30 17:00:07 CET",
      "time_utc": "2026-04-30T15:00:07Z",
      "age_seconds": 6,
      "freshness": "OK",
      "last": 27283.0,
      "bid": 27282.75,
      "ask": 27283.5,
      "mid": 27283.125,
      "close": 27325.25,
      "change_abs": -42.25,
      "change_pct": -0.15,
      "session": {
        "overnight_open": 27207.0,
        "overnight_high": 27622.75,
        "overnight_low": 27163.25,
        "prior_rth_close": 27325.25,
        "europe_open_price": 27223.5,
        "us_open_price": 27522.75,
        "move_since_europe_open_pct": 0.22,
        "move_since_us_open_pct": -0.87,
        "overnight_range_points": 459.5,
        "overnight_position_in_range": 0.261
      },
      "derived": {
        "direction_vs_close": "down",
        "overnight_regime": "trend_down",
        "above_prior_rth_close": false,
        "above_europe_open": true,
        "stretch_vs_close_points": -42.25,
        "stretch_vs_close_pct": -0.15
      },
      "status": "OK"
    },
    "RTY": {
      "label": "Russell 2000 Futures",
      "root_symbol": "RTY",
      "provider_symbol": "RTYM6",
      "exchange": "CME",
      "asset_class": "future",
      "currency": "USD",
      "time": "2026-04-30 17:00:10 CET",
      "time_utc": "2026-04-30T15:00:10Z",
      "age_seconds": 9,
      "freshness": "OK",
      "last": 2777.5,
      "bid": 2777.4,
      "ask": 2777.6,
      "mid": 2777.5,
      "close": 2747.8,
      "change_abs": 29.7,
      "change_pct": 1.08,
      "session": {
        "overnight_open": 2739.0,
        "overnight_high": 2778.7,
        "overnight_low": 2726.1,
        "prior_rth_close": 2747.8,
        "europe_open_price": 2731.4,
        "us_open_price": 2751.7,
        "move_since_europe_open_pct": 1.69,
        "move_since_us_open_pct": 0.94,
        "overnight_range_points": 52.6,
        "overnight_position_in_range": 0.977
      },
      "derived": {
        "direction_vs_close": "up",
        "overnight_regime": "trend_up",
        "above_prior_rth_close": true,
        "above_europe_open": true,
        "stretch_vs_close_points": 29.7,
        "stretch_vs_close_pct": 1.08
      },
      "status": "OK"
    },
    "YM": {
      "label": "Dow Jones Futures",
      "root_symbol": "YM",
      "provider_symbol": "YMM6",
      "exchange": "CBOT",
      "asset_class": "future",
      "currency": "USD",
      "time": "2026-04-30 17:00:13 CET",
      "time_utc": "2026-04-30T15:00:13Z",
      "age_seconds": 12,
      "freshness": "OK",
      "last": 49596.0,
      "bid": 49595.0,
      "ask": 49598.0,
      "mid": 49596.5,
      "close": 49012.0,
      "change_abs": 584.0,
      "change_pct": 1.19,
      "session": {
        "overnight_open": 48822.0,
        "overnight_high": 49635.0,
        "overnight_low": 48608.0,
        "prior_rth_close": 49012.0,
        "europe_open_price": 48688.0,
        "us_open_price": 49315.0,
        "move_since_europe_open_pct": 1.86,
        "move_since_us_open_pct": 0.57,
        "overnight_range_points": 1027.0,
        "overnight_position_in_range": 0.962
      },
      "derived": {
        "direction_vs_close": "up",
        "overnight_regime": "trend_up",
        "above_prior_rth_close": true,
        "above_europe_open": true,
        "stretch_vs_close_points": 584.0,
        "stretch_vs_close_pct": 1.19
      },
      "status": "OK"
    },
    "CL": {
      "label": "Crude Oil Futures",
      "root_symbol": "CL",
      "provider_symbol": "CLM6",
      "exchange": "NYMEX",
      "asset_class": "future",
      "currency": "USD",
      "time": "2026-04-30 17:00:16 CET",
      "time_utc": "2026-04-30T15:00:16Z",
      "age_seconds": 15,
      "freshness": "OK",
      "last": 105.99,
      "bid": 105.97,
      "ask": 105.99,
      "mid": 105.98,
      "close": 106.88,
      "change_abs": -0.89,
      "change_pct": -0.83,
      "session": {
        "overnight_open": 109.07,
        "overnight_high": 110.93,
        "overnight_low": 103.5,
        "prior_rth_close": 106.88,
        "europe_open_price": 109.37,
        "us_open_price": 105.3,
        "move_since_europe_open_pct": -3.09,
        "move_since_us_open_pct": 0.66,
        "overnight_range_points": 7.43,
        "overnight_position_in_range": 0.335
      },
      "derived": {
        "direction_vs_close": "down",
        "overnight_regime": "balanced",
        "above_prior_rth_close": false,
        "above_europe_open": false,
        "stretch_vs_close_points": -0.89,
        "stretch_vs_close_pct": -0.83
      },
      "status": "OK"
    },
    "GC": {
      "label": "Gold Futures",
      "root_symbol": "GC",
      "provider_symbol": "GCK6",
      "exchange": "COMEX",
      "asset_class": "future",
      "currency": "USD",
      "time": "2026-04-30 17:00:19 CET",
      "time_utc": "2026-04-30T15:00:19Z",
      "age_seconds": 18,
      "freshness": "OK",
      "last": 4611.9,
      "bid": 4617.6,
      "ask": 4618.5,
      "mid": 4618.05,
      "close": 4545.2,
      "change_abs": 66.7,
      "change_pct": 1.47,
      "session": {
        "overnight_open": 4561.9,
        "overnight_high": 4636.7,
        "overnight_low": 4561.9,
        "prior_rth_close": 4545.2,
        "europe_open_price": 4561.9,
        "us_open_price": 4611.6,
        "move_since_europe_open_pct": 1.1,
        "move_since_us_open_pct": 0.01,
        "overnight_range_points": 74.8,
        "overnight_position_in_range": 0.668
      },
      "derived": {
        "direction_vs_close": "up",
        "overnight_regime": "balanced",
        "above_prior_rth_close": true,
        "above_europe_open": true,
        "stretch_vs_close_points": 66.7,
        "stretch_vs_close_pct": 1.47
      },
      "status": "OK"
    },
    "ZN": {
      "label": "10Y Treasury Futures",
      "root_symbol": "ZN",
      "provider_symbol": "ZNM6",
      "exchange": "CBOT",
      "asset_class": "future",
      "currency": "USD",
      "time": "2026-04-30 17:00:23 CET",
      "time_utc": "2026-04-30T15:00:23Z",
      "age_seconds": 22,
      "freshness": "OK",
      "last": 110.578125,
      "bid": 110.578125,
      "ask": 110.59375,
      "mid": 110.5859,
      "close": 110.359375,
      "change_abs": 0.2188,
      "change_pct": 0.2,
      "session": {
        "overnight_open": 110.28125,
        "overnight_high": 110.65625,
        "overnight_low": 110.234375,
        "prior_rth_close": 110.359375,
        "europe_open_price": 110.265625,
        "us_open_price": 110.5625,
        "move_since_europe_open_pct": 0.28,
        "move_since_us_open_pct": 0.01,
        "overnight_range_points": 0.4219,
        "overnight_position_in_range": 0.815
      },
      "derived": {
        "direction_vs_close": "up",
        "overnight_regime": "trend_up",
        "above_prior_rth_close": true,
        "above_europe_open": true,
        "stretch_vs_close_points": 0.2188,
        "stretch_vs_close_pct": 0.2
      },
      "status": "OK"
    },
    "ZT": {
      "label": "2Y Treasury Futures",
      "root_symbol": "ZT",
      "provider_symbol": "ZTM6",
      "exchange": "CBOT",
      "asset_class": "future",
      "currency": "USD",
      "time": "2026-04-30 17:00:26 CET",
      "time_utc": "2026-04-30T15:00:26Z",
      "age_seconds": 25,
      "freshness": "OK",
      "last": 103.55078125,
      "bid": 103.546875,
      "ask": 103.55078125,
      "mid": 103.5488,
      "close": 103.4765625,
      "change_abs": 0.0742,
      "change_pct": 0.07,
      "session": {
        "overnight_open": 103.44921875,
        "overnight_high": 103.5703125,
        "overnight_low": 103.44140625,
        "prior_rth_close": 103.4765625,
        "europe_open_price": 103.45703125,
        "us_open_price": 103.54296875,
        "move_since_europe_open_pct": 0.09,
        "move_since_us_open_pct": 0.01,
        "overnight_range_points": 0.1289,
        "overnight_position_in_range": 0.848
      },
      "derived": {
        "direction_vs_close": "up",
        "overnight_regime": "trend_up",
        "above_prior_rth_close": true,
        "above_europe_open": true,
        "stretch_vs_close_points": 0.0742,
        "stretch_vs_close_pct": 0.07
      },
      "status": "OK"
    },
    "DX": {
      "label": "US Dollar Index Futures",
      "root_symbol": "DX",
      "provider_symbol": "DXM6",
      "exchange": "NYBOT",
      "asset_class": "future",
      "currency": "USD",
      "time": "2026-04-30 17:00:29 CET",
      "time_utc": "2026-04-30T15:00:29Z",
      "age_seconds": 28,
      "freshness": "OK",
      "last": 98.155,
      "bid": 98.15,
      "ask": 98.155,
      "mid": 98.1525,
      "close": 98.825,
      "change_abs": -0.67,
      "change_pct": -0.68,
      "session": {
        "overnight_open": 98.74,
        "overnight_high": 98.965,
        "overnight_low": 98.07,
        "prior_rth_close": 98.825,
        "europe_open_price": 98.95,
        "us_open_price": 98.325,
        "move_since_europe_open_pct": -0.8,
        "move_since_us_open_pct": -0.17,
        "overnight_range_points": 0.895,
        "overnight_position_in_range": 0.095
      },
      "derived": {
        "direction_vs_close": "down",
        "overnight_regime": "trend_down",
        "above_prior_rth_close": false,
        "above_europe_open": false,
        "stretch_vs_close_points": -0.67,
        "stretch_vs_close_pct": -0.68
      },
      "status": "OK"
    },
    "VIX": {
      "label": "VIX Futures",
      "root_symbol": "VIX",
      "provider_symbol": "VX18K6",
      "exchange": "CFE",
      "asset_class": "future",
      "currency": "USD",
      "time": "2026-04-30 17:00:32 CET",
      "time_utc": "2026-04-30T15:00:32Z",
      "age_seconds": 31,
      "freshness": "OK",
      "last": 20.25,
      "bid": 15.75,
      "ask": 21.0,
      "mid": 18.375,
      "close": 20.25,
      "change_abs": 0.0,
      "change_pct": 0.0,
      "session": {
        "overnight_open": null,
        "overnight_high": null,
        "overnight_low": null,
        "prior_rth_close": 20.25,
        "europe_open_price": null,
        "us_open_price": null,
        "move_since_europe_open_pct": null,
        "move_since_us_open_pct": null,
        "overnight_range_points": null,
        "overnight_position_in_range": null
      },
      "derived": {
        "direction_vs_close": "flat",
        "overnight_regime": null,
        "above_prior_rth_close": false,
        "above_europe_open": null,
        "stretch_vs_close_points": 0.0,
        "stretch_vs_close_pct": 0.0
      },
      "status": "OK"
    },
    "DAX": {
      "label": "DAX Futures",
      "root_symbol": "DAX",
      "provider_symbol": "FDXM 20260619 M",
      "exchange": "EUREX",
      "asset_class": "future",
      "currency": "EUR",
      "time": "2026-04-30 17:00:35 CET",
      "time_utc": "2026-04-30T15:00:35Z",
      "age_seconds": 34,
      "freshness": "OK",
      "last": 24324.0,
      "bid": 24322.0,
      "ask": 24324.0,
      "mid": 24323.0,
      "close": 24052.0,
      "change_abs": 272.0,
      "change_pct": 1.13,
      "session": {
        "overnight_open": 23997.0,
        "overnight_high": 24338.0,
        "overnight_low": 23728.0,
        "prior_rth_close": 24052.0,
        "europe_open_price": 23793.0,
        "us_open_price": 24276.0,
        "move_since_europe_open_pct": 2.23,
        "move_since_us_open_pct": 0.2,
        "overnight_range_points": 610.0,
        "overnight_position_in_range": 0.977
      },
      "derived": {
        "direction_vs_close": "up",
        "overnight_regime": "trend_up",
        "above_prior_rth_close": true,
        "above_europe_open": true,
        "stretch_vs_close_points": 272.0,
        "stretch_vs_close_pct": 1.13
      },
      "status": "OK"
    },
    "ESTX50": {
      "label": "Euro Stoxx 50 Futures",
      "root_symbol": "ESTX50",
      "provider_symbol": "FESX 20260619 M",
      "exchange": "EUREX",
      "asset_class": "future",
      "currency": "EUR",
      "time": "2026-04-30 17:00:38 CET",
      "time_utc": "2026-04-30T15:00:38Z",
      "age_seconds": 37,
      "freshness": "OK",
      "last": 5824.0,
      "bid": 5824.0,
      "ask": 5825.0,
      "mid": 5824.5,
      "close": 5767.0,
      "change_abs": 57.0,
      "change_pct": 0.99,
      "session": {
        "overnight_open": 5759.0,
        "overnight_high": 5828.0,
        "overnight_low": 5692.0,
        "prior_rth_close": 5767.0,
        "europe_open_price": 5708.0,
        "us_open_price": 5802.0,
        "move_since_europe_open_pct": 2.03,
        "move_since_us_open_pct": 0.38,
        "overnight_range_points": 136.0,
        "overnight_position_in_range": 0.971
      },
      "derived": {
        "direction_vs_close": "up",
        "overnight_regime": "trend_up",
        "above_prior_rth_close": true,
        "above_europe_open": true,
        "stretch_vs_close_points": 57.0,
        "stretch_vs_close_pct": 0.99
      },
      "status": "OK"
    },
    "NKD": {
      "label": "Nikkei 225 Futures",
      "root_symbol": "NKD",
      "provider_symbol": "NKDM6",
      "exchange": "CME",
      "asset_class": "future",
      "currency": "USD",
      "time": "2026-04-30 17:00:41 CET",
      "time_utc": "2026-04-30T15:00:41Z",
      "age_seconds": 40,
      "freshness": "OK",
      "last": 59530.0,
      "bid": 59525.0,
      "ask": 59535.0,
      "mid": 59530.0,
      "close": 58925.0,
      "change_abs": 605.0,
      "change_pct": 1.03,
      "session": {
        "overnight_open": 58690.0,
        "overnight_high": 59710.0,
        "overnight_low": 58655.0,
        "prior_rth_close": 58925.0,
        "europe_open_price": 59215.0,
        "us_open_price": 59370.0,
        "move_since_europe_open_pct": 0.53,
        "move_since_us_open_pct": 0.27,
        "overnight_range_points": 1055.0,
        "overnight_position_in_range": 0.829
      },
      "derived": {
        "direction_vs_close": "up",
        "overnight_regime": "trend_up",
        "above_prior_rth_close": true,
        "above_europe_open": true,
        "stretch_vs_close_points": 605.0,
        "stretch_vs_close_pct": 1.03
      },
      "status": "OK"
    },
    "EURUSD": {
      "label": "Euro / US Dollar",
      "root_symbol": "EURUSD",
      "provider_symbol": "EURUSD",
      "exchange": "IDEALPRO",
      "asset_class": "fx",
      "currency": "USD",
      "time": "2026-04-30 17:00:43 CET",
      "time_utc": "2026-04-30T15:00:43Z",
      "age_seconds": 42,
      "freshness": "OK",
      "last": 1.1729,
      "bid": 1.17288,
      "ask": 1.17289,
      "mid": 1.172885,
      "close": 1.1675,
      "change_abs": 0.0054,
      "change_pct": 0.4625,
      "session": null,
      "derived": null,
      "status": "OK"
    },
    "USDJPY": {
      "label": "US Dollar / Japanese Yen",
      "root_symbol": "USDJPY",
      "provider_symbol": "USDJPY",
      "exchange": "IDEALPRO",
      "asset_class": "fx",
      "currency": "JPY",
      "time": "2026-04-30 17:00:45 CET",
      "time_utc": "2026-04-30T15:00:45Z",
      "age_seconds": 44,
      "freshness": "OK",
      "last": 156.71,
      "bid": 156.712,
      "ask": 156.714,
      "mid": 156.713,
      "close": 160.45,
      "change_abs": -3.74,
      "change_pct": -2.3309,
      "session": null,
      "derived": null,
      "status": "OK"
    },
    "XLK": {
      "label": "SPDR Technology ETF",
      "root_symbol": "XLK",
      "provider_symbol": "XLK",
      "exchange": "SMART",
      "asset_class": "etf",
      "sector": "Technology",
      "classification": "offensive",
      "currency": "USD",
      "time": "2026-04-30 17:00:47 CET",
      "time_utc": "2026-04-30T15:00:47Z",
      "age_seconds": 46,
      "freshness": "OK",
      "last": null,
      "bid": null,
      "ask": null,
      "mid": null,
      "close": null,
      "change_abs": null,
      "change_pct": null,
      "session": null,
      "derived": null,
      "status": "NO_DATA"
    },
    "XLF": {
      "label": "SPDR Financials ETF",
      "root_symbol": "XLF",
      "provider_symbol": "XLF",
      "exchange": "SMART",
      "asset_class": "etf",
      "sector": "Financials",
      "classification": "offensive",
      "currency": "USD",
      "time": "2026-04-30 17:00:49 CET",
      "time_utc": "2026-04-30T15:00:49Z",
      "age_seconds": 48,
      "freshness": "OK",
      "last": null,
      "bid": null,
      "ask": null,
      "mid": null,
      "close": null,
      "change_abs": null,
      "change_pct": null,
      "session": null,
      "derived": null,
      "status": "NO_DATA"
    },
    "XLV": {
      "label": "SPDR Health Care ETF",
      "root_symbol": "XLV",
      "provider_symbol": "XLV",
      "exchange": "SMART",
      "asset_class": "etf",
      "sector": "Health Care",
      "classification": "defensive",
      "currency": "USD",
      "time": "2026-04-30 17:00:51 CET",
      "time_utc": "2026-04-30T15:00:51Z",
      "age_seconds": 50,
      "freshness": "OK",
      "last": null,
      "bid": null,
      "ask": null,
      "mid": null,
      "close": null,
      "change_abs": null,
      "change_pct": null,
      "session": null,
      "derived": null,
      "status": "NO_DATA"
    },
    "XLY": {
      "label": "SPDR Consumer Discretionary ETF",
      "root_symbol": "XLY",
      "provider_symbol": "XLY",
      "exchange": "SMART",
      "asset_class": "etf",
      "sector": "Consumer Discretionary",
      "classification": "offensive",
      "currency": "USD",
      "time": "2026-04-30 17:00:53 CET",
      "time_utc": "2026-04-30T15:00:53Z",
      "age_seconds": 52,
      "freshness": "OK",
      "last": null,
      "bid": null,
      "ask": null,
      "mid": null,
      "close": null,
      "change_abs": null,
      "change_pct": null,
      "session": null,
      "derived": null,
      "status": "NO_DATA"
    },
    "XLP": {
      "label": "SPDR Consumer Staples ETF",
      "root_symbol": "XLP",
      "provider_symbol": "XLP",
      "exchange": "SMART",
      "asset_class": "etf",
      "sector": "Consumer Staples",
      "classification": "defensive",
      "currency": "USD",
      "time": "2026-04-30 17:00:55 CET",
      "time_utc": "2026-04-30T15:00:55Z",
      "age_seconds": 54,
      "freshness": "OK",
      "last": null,
      "bid": null,
      "ask": null,
      "mid": null,
      "close": null,
      "change_abs": null,
      "change_pct": null,
      "session": null,
      "derived": null,
      "status": "NO_DATA"
    },
    "XLE": {
      "label": "SPDR Energy ETF",
      "root_symbol": "XLE",
      "provider_symbol": "XLE",
      "exchange": "SMART",
      "asset_class": "etf",
      "sector": "Energy",
      "classification": "offensive",
      "currency": "USD",
      "time": "2026-04-30 17:00:57 CET",
      "time_utc": "2026-04-30T15:00:57Z",
      "age_seconds": 56,
      "freshness": "OK",
      "last": null,
      "bid": null,
      "ask": null,
      "mid": null,
      "close": null,
      "change_abs": null,
      "change_pct": null,
      "session": null,
      "derived": null,
      "status": "NO_DATA"
    },
    "XLI": {
      "label": "SPDR Industrials ETF",
      "root_symbol": "XLI",
      "provider_symbol": "XLI",
      "exchange": "SMART",
      "asset_class": "etf",
      "sector": "Industrials",
      "classification": "offensive",
      "currency": "USD",
      "time": "2026-04-30 17:00:59 CET",
      "time_utc": "2026-04-30T15:00:59Z",
      "age_seconds": 58,
      "freshness": "OK",
      "last": null,
      "bid": null,
      "ask": null,
      "mid": null,
      "close": null,
      "change_abs": null,
      "change_pct": null,
      "session": null,
      "derived": null,
      "status": "NO_DATA"
    },
    "XLB": {
      "label": "SPDR Materials ETF",
      "root_symbol": "XLB",
      "provider_symbol": "XLB",
      "exchange": "SMART",
      "asset_class": "etf",
      "sector": "Materials",
      "classification": "offensive",
      "currency": "USD",
      "time": "2026-04-30 17:01:01 CET",
      "time_utc": "2026-04-30T15:01:01Z",
      "age_seconds": 60,
      "freshness": "OK",
      "last": null,
      "bid": null,
      "ask": null,
      "mid": null,
      "close": null,
      "change_abs": null,
      "change_pct": null,
      "session": null,
      "derived": null,
      "status": "NO_DATA"
    },
    "XLRE": {
      "label": "SPDR Real Estate ETF",
      "root_symbol": "XLRE",
      "provider_symbol": "XLRE",
      "exchange": "SMART",
      "asset_class": "etf",
      "sector": "Real Estate",
      "classification": "defensive",
      "currency": "USD",
      "time": "2026-04-30 17:01:03 CET",
      "time_utc": "2026-04-30T15:01:03Z",
      "age_seconds": 62,
      "freshness": "OK",
      "last": 44.11,
      "bid": 44.1,
      "ask": 44.11,
      "mid": 44.105,
      "close": 43.64,
      "change_abs": 0.47,
      "change_pct": 1.08,
      "session": null,
      "derived": null,
      "status": "OK"
    },
    "XLU": {
      "label": "SPDR Utilities ETF",
      "root_symbol": "XLU",
      "provider_symbol": "XLU",
      "exchange": "SMART",
      "asset_class": "etf",
      "sector": "Utilities",
      "classification": "defensive",
      "currency": "USD",
      "time": "2026-04-30 17:01:05 CET",
      "time_utc": "2026-04-30T15:01:05Z",
      "age_seconds": 64,
      "freshness": "OK",
      "last": 46.77,
      "bid": 46.76,
      "ask": 46.77,
      "mid": 46.765,
      "close": 45.68,
      "change_abs": 1.09,
      "change_pct": 2.39,
      "session": null,
      "derived": null,
      "status": "OK"
    },
    "XLC": {
      "label": "SPDR Communication Services ETF",
      "root_symbol": "XLC",
      "provider_symbol": "XLC",
      "exchange": "SMART",
      "asset_class": "etf",
      "sector": "Communication Services",
      "classification": "offensive",
      "currency": "USD",
      "time": "2026-04-30 17:01:08 CET",
      "time_utc": "2026-04-30T15:01:08Z",
      "age_seconds": 67,
      "freshness": "OK",
      "last": null,
      "bid": null,
      "ask": null,
      "mid": null,
      "close": null,
      "change_abs": null,
      "change_pct": null,
      "session": null,
      "derived": null,
      "status": "NO_DATA"
    },
    "HYG": {
      "label": "iShares High Yield Corp Bond ETF",
      "root_symbol": "HYG",
      "provider_symbol": "HYG",
      "exchange": "SMART",
      "asset_class": "etf",
      "credit_type": "high_yield",
      "currency": "USD",
      "time": "2026-04-30 17:01:10 CET",
      "time_utc": "2026-04-30T15:01:10Z",
      "age_seconds": 69,
      "freshness": "OK",
      "last": 80.28,
      "bid": 80.27,
      "ask": 80.28,
      "mid": 80.275,
      "close": 80.13,
      "change_abs": 0.15,
      "change_pct": 0.19,
      "session": null,
      "derived": null,
      "status": "OK"
    },
    "JNK": {
      "label": "SPDR Bloomberg High Yield Bond ETF",
      "root_symbol": "JNK",
      "provider_symbol": "JNK",
      "exchange": "SMART",
      "asset_class": "etf",
      "credit_type": "high_yield",
      "currency": "USD",
      "time": "2026-04-30 17:01:12 CET",
      "time_utc": "2026-04-30T15:01:12Z",
      "age_seconds": 71,
      "freshness": "OK",
      "last": 96.68,
      "bid": 96.68,
      "ask": 96.68,
      "mid": 96.68,
      "close": 96.5,
      "change_abs": 0.18,
      "change_pct": 0.19,
      "session": null,
      "derived": null,
      "status": "OK"
    },
    "LQD": {
      "label": "iShares Investment Grade Corp Bond ETF",
      "root_symbol": "LQD",
      "provider_symbol": "LQD",
      "exchange": "SMART",
      "asset_class": "etf",
      "credit_type": "invest_grade",
      "currency": "USD",
      "time": "2026-04-30 17:01:14 CET",
      "time_utc": "2026-04-30T15:01:14Z",
      "age_seconds": 73,
      "freshness": "OK",
      "last": null,
      "bid": null,
      "ask": null,
      "mid": null,
      "close": null,
      "change_abs": null,
      "change_pct": null,
      "session": null,
      "derived": null,
      "status": "NO_DATA"
    },
    "TLT": {
      "label": "iShares 20+ Year Treasury Bond ETF",
      "root_symbol": "TLT",
      "provider_symbol": "TLT",
      "exchange": "SMART",
      "asset_class": "etf",
      "credit_type": "treasury",
      "currency": "USD",
      "time": "2026-04-30 17:01:16 CET",
      "time_utc": "2026-04-30T15:01:16Z",
      "age_seconds": 75,
      "freshness": "OK",
      "last": 85.76,
      "bid": 85.76,
      "ask": 85.77,
      "mid": 85.765,
      "close": 85.7,
      "change_abs": 0.06,
      "change_pct": 0.07,
      "session": null,
      "derived": null,
      "status": "OK"
    },
    "IEF": {
      "label": "iShares 7-10 Year Treasury Bond ETF",
      "root_symbol": "IEF",
      "provider_symbol": "IEF",
      "exchange": "SMART",
      "asset_class": "etf",
      "credit_type": "treasury",
      "currency": "USD",
      "time": "2026-04-30 17:01:18 CET",
      "time_utc": "2026-04-30T15:01:18Z",
      "age_seconds": 77,
      "freshness": "OK",
      "last": 94.98,
      "bid": 94.98,
      "ask": 94.99,
      "mid": 94.985,
      "close": 94.8,
      "change_abs": 0.18,
      "change_pct": 0.19,
      "session": null,
      "derived": null,
      "status": "OK"
    }
  },
  "truth_tellers": {
    "primary": [
      "USDJPY",
      "GC",
      "YM",
      "DAX"
    ],
    "secondary": [
      "RTY",
      "NKD",
      "ESTX50"
    ],
    "notes": "No notable divergences."
  },
  "alerts": [
    {
      "level": "info",
      "code": "ES_ABOVE_PRIOR_CLOSE",
      "message": "ES trading above prior RTH close."
    },
    {
      "level": "warning",
      "code": "SECTOR_BREADTH_WEAK",
      "message": "Only 2/11 sectors advancing \u2014 narrow rally."
    }
  ],
  "errors": []
}